odoo/addons/delivery_auto_refresh/README.rst
odoo/addons/delivery_auto_refresh/__init__.py
odoo/addons/delivery_auto_refresh/__manifest__.py
odoo/addons/delivery_auto_refresh/i18n/ca.po
odoo/addons/delivery_auto_refresh/i18n/cs_CZ.po
odoo/addons/delivery_auto_refresh/i18n/de.po
odoo/addons/delivery_auto_refresh/i18n/delivery_auto_refresh.pot
odoo/addons/delivery_auto_refresh/i18n/el_GR.po
odoo/addons/delivery_auto_refresh/i18n/es.po
odoo/addons/delivery_auto_refresh/i18n/es_ES.po
odoo/addons/delivery_auto_refresh/i18n/es_VE.po
odoo/addons/delivery_auto_refresh/i18n/fi.po
odoo/addons/delivery_auto_refresh/i18n/fr.po
odoo/addons/delivery_auto_refresh/i18n/gl.po
odoo/addons/delivery_auto_refresh/i18n/hr.po
odoo/addons/delivery_auto_refresh/i18n/hr_HR.po
odoo/addons/delivery_auto_refresh/i18n/hu.po
odoo/addons/delivery_auto_refresh/i18n/it.po
odoo/addons/delivery_auto_refresh/i18n/nl.po
odoo/addons/delivery_auto_refresh/i18n/nl_NL.po
odoo/addons/delivery_auto_refresh/i18n/pt.po
odoo/addons/delivery_auto_refresh/i18n/pt_BR.po
odoo/addons/delivery_auto_refresh/i18n/ro.po
odoo/addons/delivery_auto_refresh/i18n/sl.po
odoo/addons/delivery_auto_refresh/i18n/tr.po
odoo/addons/delivery_auto_refresh/i18n/tr_TR.po
odoo/addons/delivery_auto_refresh/i18n/vi_VN.po
odoo/addons/delivery_auto_refresh/i18n/zh_CN.po
odoo/addons/delivery_auto_refresh/models/__init__.py
odoo/addons/delivery_auto_refresh/models/res_company.py
odoo/addons/delivery_auto_refresh/models/res_config_settings.py
odoo/addons/delivery_auto_refresh/models/sale_order.py
odoo/addons/delivery_auto_refresh/models/stock_picking.py
odoo/addons/delivery_auto_refresh/readme/CONFIGURE.md
odoo/addons/delivery_auto_refresh/readme/CONTRIBUTORS.md
odoo/addons/delivery_auto_refresh/readme/DESCRIPTION.md
odoo/addons/delivery_auto_refresh/readme/ROADMAP.md
odoo/addons/delivery_auto_refresh/static/description/icon.png
odoo/addons/delivery_auto_refresh/static/description/index.html
odoo/addons/delivery_auto_refresh/tests/__init__.py
odoo_addon_delivery_auto_refresh-18.0.1.0.0.2.dist-info/METADATA
odoo_addon_delivery_auto_refresh-18.0.1.0.0.2.dist-info/WHEEL
odoo_addon_delivery_auto_refresh-18.0.1.0.0.2.dist-info/top_level.txt
odoo_addon_delivery_auto_refresh-18.0.1.0.0.2.dist-info/RECORD
